polus/__init__.py
polus/polus_render.py
polus/render_server.py
polus/apps/render-ui/222.9e2b8d463f9bedcb.js
polus/apps/render-ui/227.3f1a8f5ca9e24b96.js
polus/apps/render-ui/3rdpartylicenses.txt
polus/apps/render-ui/482.b9f0a670e0abc289.js
polus/apps/render-ui/5.c411a729ee201d46.js
polus/apps/render-ui/625.121743b98d40ec89.js
polus/apps/render-ui/750.10c07e8236842850.js
polus/apps/render-ui/828.ca35a89bb5fc2cae.js
polus/apps/render-ui/906.78eeb630ad2b9f79.js
polus/apps/render-ui/941.a0ef451f387b9c4b.js
polus/apps/render-ui/favicon.ico
polus/apps/render-ui/index.html
polus/apps/render-ui/main.0534b4df0601b220.js
polus/apps/render-ui/main.76f44d98b6f2749c.js
polus/apps/render-ui/main.ad93806391356ebf.js
polus/apps/render-ui/polyfills.c4e865107f304558.js
polus/apps/render-ui/runtime.585eb23275837cbc.js
polus/apps/render-ui/styles.ab1d78fd50d9dfd6.css
polus/apps/render-ui/assets/config.json
polus/apps/updog-render/.DS_Store
polus/apps/updog-render/LICENSE
polus/apps/updog-render/MANIFEST.in
polus/apps/updog-render/README.md
polus/apps/updog-render/requirements.txt
polus/apps/updog-render/setup.cfg
polus/apps/updog-render/setup.py
polus/apps/updog-render/updog/.DS_Store
polus/apps/updog-render/updog/__init__.py
polus/apps/updog-render/updog/__main__.py
polus/apps/updog-render/updog/static/.DS_Store
polus/apps/updog-render/updog/static/css/bootstrap.min.css
polus/apps/updog-render/updog/static/css/font.scss
polus/apps/updog-render/updog/static/css/style.min.css
polus/apps/updog-render/updog/static/css/style.scss
polus/apps/updog-render/updog/static/fonts/poppins/poppins-v5-latin-300.eot
polus/apps/updog-render/updog/static/fonts/poppins/poppins-v5-latin-300.svg
polus/apps/updog-render/updog/static/fonts/poppins/poppins-v5-latin-300.ttf
polus/apps/updog-render/updog/static/fonts/poppins/poppins-v5-latin-300.woff
polus/apps/updog-render/updog/static/fonts/poppins/poppins-v5-latin-300.woff2
polus/apps/updog-render/updog/static/fonts/poppins/poppins-v5-latin-600.eot
localhost_server_polus_render-0.1.0.dist-info/LICENSE
localhost_server_polus_render-0.1.0.dist-info/METADATA
localhost_server_polus_render-0.1.0.dist-info/WHEEL
localhost_server_polus_render-0.1.0.dist-info/top_level.txt
localhost_server_polus_render-0.1.0.dist-info/RECORD
